cant/__init__.py
cant/alpha_status.py
cant/arity.py
cant/comparison_functions.py
cant/get_callables.py
cant/rem.py
cant/tests/__init__.py
cant/tests/run_tests.py
cant-0.0.dist-info/DESCRIPTION.rst
cant-0.0.dist-info/METADATA
cant-0.0.dist-info/RECORD
cant-0.0.dist-info/WHEEL
cant-0.0.dist-info/metadata.json
cant-0.0.dist-info/top_level.txt
